.DS_Store
plm/.DS_Store
plm/__init__.py
plm/__main__.py
plm/__version__.py
plm/plm.py
plm_dgraham-0.4.0.dist-info/METADATA
plm_dgraham-0.4.0.dist-info/WHEEL
plm_dgraham-0.4.0.dist-info/entry_points.txt
plm_dgraham-0.4.0.dist-info/top_level.txt
plm_dgraham-0.4.0.dist-info/RECORD
