Metadata-Version: 2.1
Name: plm-dgraham
Version: 0.4.0
Summary: player lineup manager
Home-page: https://github.com/dagraham/plm-dgraham
Author: Daniel A Graham
Author-email: dnlgrhm@gmail.com
License: GPL
Classifier: Development Status :: 5 - Production/Stable
Classifier: Environment :: Console
Classifier: Intended Audience :: End Users/Desktop
Classifier: License :: OSI Approved :: GNU General Public License (GPL)
Classifier: Programming Language :: Python
Classifier: Programming Language :: Python :: 3.7
Classifier: Programming Language :: Python :: 3.8
Classifier: Programming Language :: Python :: Implementation :: CPython
Classifier: Programming Language :: Python :: Implementation :: PyPy
Classifier: Topic :: Office/Business
Classifier: Topic :: Office/Business :: News/Diary
Classifier: Topic :: Office/Business :: Scheduling
Requires-Python: >=3.7.3
Requires-Dist: prompt-toolkit (>=3.0.24)
Requires-Dist: ruamel.yaml (>=0.15.88)
Requires-Dist: python-dateutil (>=2.7.3)
Requires-Dist: pendulum (>=2.0.4)
Requires-Dist: requests (>=2.25.1)
Requires-Dist: pyperclip (>=1.7.0)
Requires-Dist: termcolor (>=2.2.0)
